cpdf/__init__.py
cpdf/__main__.py
cpdf/_version.py
cpdf/cat.py
cpdf/cli.py
cpdf/extract_images.py
cpdf/metadata.py
cpdf/up2.py
cpdf-0.0.7.dist-info/LICENSE
cpdf-0.0.7.dist-info/METADATA
cpdf-0.0.7.dist-info/WHEEL
cpdf-0.0.7.dist-info/entry_points.txt
cpdf-0.0.7.dist-info/top_level.txt
cpdf-0.0.7.dist-info/RECORD
