Metadata-Version: 2.1
Name: cpdf
Version: 0.0.7
Summary: A pure-python CLI application to manipulate PDF files
Home-page: https://github.com/py-pdf/cpdf
Author: Martin Thoma
Author-email: info@martin-thoma.de
Maintainer: Martin Thoma
Maintainer-email: info@martin-thoma.de
License: BSD-3-Clause
Keywords: pdf,pure-python
Platform: UNKNOWN
Classifier: Development Status :: 1 - Planning
Classifier: Environment :: Console
Classifier: Intended Audience :: Developers
Classifier: License :: OSI Approved :: MIT License
Classifier: Natural Language :: English
Classifier: Operating System :: OS Independent
Classifier: Programming Language :: Python :: 3
Classifier: Programming Language :: Python :: 3 :: Only
Classifier: Programming Language :: Python :: 3.7
Classifier: Programming Language :: Python :: 3.8
Classifier: Programming Language :: Python :: 3.9
Classifier: Programming Language :: Python :: 3.10
Requires-Python: >=3.6.1
License-File: LICENSE
Requires-Dist: PyPDF2
Requires-Dist: typer
Requires-Dist: pillow
Requires-Dist: pydantic
Requires-Dist: rich
